finance_ops_scripts-0.3.2.dist-info/licenses/LICENSE.txt
scripts/python/__init__.py
scripts/python/ramp_export_mapper.py
finance_ops_scripts-0.3.2.dist-info/METADATA
finance_ops_scripts-0.3.2.dist-info/WHEEL
finance_ops_scripts-0.3.2.dist-info/entry_points.txt
finance_ops_scripts-0.3.2.dist-info/top_level.txt
finance_ops_scripts-0.3.2.dist-info/RECORD
