Metadata-Version: 2.4
Name: finance-ops-scripts
Version: 0.3.2
Summary: Finance operations automation scripts for ramp export mapping and related workflows.
Author-email: Zachary Place <your.email@domain.com>
License-Expression: MIT
Project-URL: Homepage, https://github.com/mvp-zplace/finance-ops-scripts
Project-URL: Documentation, https://github.com/mvp-zplace/finance-ops-scripts#readme
Project-URL: Issues, https://github.com/mvp-zplace/finance-ops-scripts/issues
Project-URL: Source, https://github.com/mvp-zplace/finance-ops-scripts
Keywords: finance,operations,automation,ramp,mapping,csv,cli
Classifier: Development Status :: 5 - Production/Stable
Classifier: Intended Audience :: Financial and Insurance Industry
Classifier: Intended Audience :: Developers
Classifier: Topic :: Office/Business :: Financial :: Accounting
Classifier: Topic :: Software Development :: Build Tools
Classifier: Programming Language :: Python :: 3
Classifier: Programming Language :: Python :: 3.10
Classifier: Programming Language :: Python :: 3.11
Classifier: Programming Language :: Python :: 3.12
Requires-Python: >=3.10
License-File: LICENSE.txt
Dynamic: license-file
